[
    { 
      "id": 1, 
      "numero": 1,
      "pregunta": "¿Cuántos años hace que está el actual sistema de riesgos de trabajo en Argentina?", 
      "opciones": ["50 años","25 años","15 años"], 
      "respuestaCorrecta": 1,
      "dificultad": "basico"
    },
    { 
      "id": 2, 
      "numero": 2,
      "pregunta": "El sistema de riesgos de trabajo cubre los siniestros que sufren:", 
      "opciones": ["Los trabajadores titulares solamente en relación de dependencia","Los trabajadores y también a su grupo familiar","Los empleadores y los trabajadores"], 
      "respuestaCorrecta": 1,
      "dificultad": "basico"
    },
    { 
      "id": 3, 
      "numero": 3,
      "pregunta": "¿Cuál es la actividad que registra los mayores riesgos laborales?", 
      "opciones": ["Actividad rural","Actividad construcción","Actividad turismo"], 
      "respuestaCorrecta": 1,
      "dificultad": "basico"
    },
    { 
      "id": 4, 
      "numero": 1,
      "pregunta": "¿Cuál es la correcta definición de A.R.T.?", 
      "opciones": ["Asociación de riesgos del trabajo","Aseguradora de riesgos del trabajo","Administradora de riesgos del trabajo"], 
      "respuestaCorrecta": 2,
      "dificultad": "avanzado"
    },
    { 
      "id": 5, 
      "numero": 2,
      "pregunta": "¿Quién contrata la A.R.T.?", 
      "opciones": ["El empleador","El trabajador","El empleador y el trabajador juntos"], 
      "respuestaCorrecta": 1,
      "dificultad": "avanzado"
    },
    { 
      "id": 6, 
      "numero": 3,
      "pregunta": "¿Qué es un accidente 'in itinere'?", 
      "opciones": ["El  que sucede en el trayecto de mi hogar al trabajo y del trabajo a mi hogar","El que sucede en el ámbito del trabajo","El que sucede en mi hogar"], 
      "respuestaCorrecta": 1,
      "dificultad": "avanzado"
    },
    { 
      "id": 7, 
      "numero": 4,
      "pregunta": "El objetivo de la Ley sobre Riesgos del Trabajo es:", 
      "opciones": ["Reducir la siniestralidad laboral a través de la prevención de los riesgos derivados del trabajo.","Reparar los daños derivados de accidentes de trabajo y enfermedades profesionales.","Las dos anteriores son correctas."], 
      "respuestaCorrecta": 3,
      "dificultad": "basico"
    }
  ]